deco_slack/__init__.py
deco_slack-0.0.3.dist-info/METADATA
deco_slack-0.0.3.dist-info/WHEEL
deco_slack-0.0.3.dist-info/RECORD
