Metadata-Version: 2.3
Name: deco_slack
Version: 0.0.3
Summary: deco_slack notifies you if a method has completed successfully or not.
Author: taross-f
Author-email: taro.furuya@gmail.com
Requires-Python: >=3.7,<4.0
Classifier: Programming Language :: Python :: 3
Classifier: Programming Language :: Python :: 3.7
Classifier: Programming Language :: Python :: 3.8
Classifier: Programming Language :: Python :: 3.9
Classifier: Programming Language :: Python :: 3.10
Classifier: Programming Language :: Python :: 3.11
Classifier: Programming Language :: Python :: 3.12
Classifier: Programming Language :: Python :: 3.13
Requires-Dist: slack-sdk (>=3.3.1,<4.0.0)
Project-URL: Repository, https://github.com/taross-f/deco-slack
